[
    {
        "kanji": "刀",
        "meanings": [ "blade", "katana", "knife" ],
        "pronunciations": {
            "romaji": [],
            "hiragana": [],
            "katakana": []
        }
    },
    {
        "kanji": "万",
        "meanings": [ "ten thousand", "10000", "10 000", "10.000" ],
        "pronunciations": {
            "romaji": [],
            "hiragana": [],
            "katakana": []
        }
    },
    {
        "kanji": "丸",
        "meanings": [ "circle", "round", "whole", "pill" ],
        "pronunciations": {
            "romaji": [],
            "hiragana": [],
            "katakana": []
        }
    },
    {
        "kanji": "才",
        "meanings": [ "age" ],
        "pronunciations": {
            "romaji": [],
            "hiragana": [],
            "katakana": []
        }
    },
    {
        "kanji": "工",
        "meanings": [ "work", "craft", "art", "skill", "worksman", "artisan" ],
        "pronunciations": {
            "romaji": [],
            "hiragana": [],
            "katakana": []
        }
    },
    {
        "kanji": "弓",
        "meanings": [ "bow" ],
        "pronunciations": {
            "romaji": [],
            "hiragana": [],
            "katakana": []
        }
    },
    {
        "kanji": "内",
        "meanings": [ "inside", "within", "between", "among", "while", "during" ],
        "pronunciations": {
            "romaji": [],
            "hiragana": [],
            "katakana": []
        }
    },
    {
        "kanji": "午",
        "meanings": [ "noon", "horse" ],
        "pronunciations": {
            "romaji": [],
            "hiragana": [],
            "katakana": []
        }
    },
    {
        "kanji": "少",
        "meanings": [ "little" ],
        "pronunciations": {
            "romaji": [],
            "hiragana": [],
            "katakana": []
        }
    },
    {
        "kanji": "元",
        "meanings": [ "cause", "origin", "basis", "foundation", "cost" ],
        "pronunciations": {
            "romaji": [],
            "hiragana": [],
            "katakana": []
        }
    },
    {
        "kanji": "今",
        "meanings": [ "now" ],
        "pronunciations": {
            "romaji": [],
            "hiragana": [],
            "katakana": []
        }
    },
    {
        "kanji": "公",
        "meanings": [ "public", "official", "governmantal" ],
        "pronunciations": {
            "romaji": [],
            "hiragana": [],
            "katakana": []
        }
    },
    {
        "kanji": "分",
        "meanings": [ "minutes" ],
        "pronunciations": {
            "romaji": [],
            "hiragana": [],
            "katakana": []
        }
    },
    {
        "kanji": "切",
        "meanings": [ "cut" ],
        "pronunciations": {
            "romaji": [],
            "hiragana": [],
            "katakana": []
        }
    },
    {
        "kanji": "友",
        "meanings": [ "firend" ],
        "pronunciations": {
            "romaji": [],
            "hiragana": [],
            "katakana": []
        }
    },
    {
        "kanji": "太",
        "meanings": [ "fat", "thick" ],
        "pronunciations": {
            "romaji": [],
            "hiragana": [],
            "katakana": []
        }
    },
    {
        "kanji": "引",
        "meanings": [ "pull", "tug", "admit" ],
        "pronunciations": {
            "romaji": [],
            "hiragana": [],
            "katakana": []
        }
    },
    {
        "kanji": "心",
        "meanings": [ "mind", "heart", "spirit", "soul", "thoughts", "ideas" ],
        "pronunciations": {
            "romaji": [],
            "hiragana": [],
            "katakana": []
        }
    },
    {
        "kanji": "戸",
        "meanings": [ "door" ],
        "pronunciations": {
            "romaji": [],
            "hiragana": [],
            "katakana": []
        }
    },
    {
        "kanji": "方",
        "meanings": [ "direction", "person", "alternative" ],
        "pronunciations": {
            "romaji": [],
            "hiragana": [],
            "katakana": []
        }
    },
    {
        "kanji": "止",
        "meanings": [ "stop", "to stop" ],
        "pronunciations": {
            "romaji": [],
            "hiragana": [],
            "katakana": []
        }
    },
    {
        "kanji": "毛",
        "meanings": [ "hair", "fur" ],
        "pronunciations": {
            "romaji": [],
            "hiragana": [],
            "katakana": []
        }
    },
    {
        "kanji": "父",
        "meanings": [ "father" ],
        "pronunciations": {
            "romaji": [],
            "hiragana": [],
            "katakana": []
        }
    },
    {
        "kanji": "牛",
        "meanings": [ "cow" ],
        "pronunciations": {
            "romaji": [],
            "hiragana": [],
            "katakana": []
        }
    },
    {
        "kanji": "半",
        "meanings": [ "half" ],
        "pronunciations": {
            "romaji": [],
            "hiragana": [],
            "katakana": []
        }
    },
    {
        "kanji": "市",
        "meanings": [ "city", "market" ],
        "pronunciations": {
            "romaji": [],
            "hiragana": [],
            "katakana": []
        }
    },
    {
        "kanji": "北",
        "meanings": [ "north", "escape" ],
        "pronunciations": {
            "romaji": [],
            "hiragana": [],
            "katakana": []
        }
    },
    {
        "kanji": "古",
        "meanings": [ "old", "past", "ancient" ],
        "pronunciations": {
            "romaji": [],
            "hiragana": [],
            "katakana": []
        }
    },
    {
        "kanji": "台",
        "meanings": [ "pedestal", "stand", "Taiwan" ],
        "pronunciations": {
            "romaji": [],
            "hiragana": [],
            "katakana": []
        }
    },
    {
        "kanji": "兄",
        "meanings": [ "brother", "older brother" ],
        "pronunciations": {
            "romaji": [],
            "hiragana": [],
            "katakana": []
        }
    },
    {
        "kanji": "冬",
        "meanings": [ "winter" ],
        "pronunciations": {
            "romaji": [],
            "hiragana": [],
            "katakana": []
        }
    },
    {
        "kanji": "外",
        "meanings": [ "outside", "foreign", "other", "except" ],
        "pronunciations": {
            "romaji": [],
            "hiragana": [],
            "katakana": []
        }
    },
    {
        "kanji": "広",
        "meanings": [ "vast", "wide" ],
        "pronunciations": {
            "romaji": [],
            "hiragana": [],
            "katakana": []
        }
    },
    {
        "kanji": "母",
        "meanings": [ "mother" ],
        "pronunciations": {
            "romaji": [],
            "hiragana": [],
            "katakana": []
        }
    },
    {
        "kanji": "用",
        "meanings": [ "use", "task", "errand", "business" ],
        "pronunciations": {
            "romaji": [],
            "hiragana": [],
            "katakana": []
        }
    },
    {
        "kanji": "矢",
        "meanings": [ "arrow" ],
        "pronunciations": {
            "romaji": [],
            "hiragana": [],
            "katakana": []
        }
    },
    {
        "kanji": "交",
        "meanings": [ "intersect", "to intersect", "to cross", "exchange" ],
        "pronunciations": {
            "romaji": [],
            "hiragana": [],
            "katakana": []
        }
    },
    {
        "kanji": "会",
        "meanings": [ "meeting", "gathering", "society", "association", "club", "party" ],
        "pronunciations": {
            "romaji": [],
            "hiragana": [],
            "katakana": []
        }
    },
    {
        "kanji": "合",
        "meanings": [ "fit", "suit", "join", "together", "one tenth" ],
        "pronunciations": {
            "romaji": [],
            "hiragana": [],
            "katakana": []
        }
    },
    {
        "kanji": "同",
        "meanings": [ "same" ],
        "pronunciations": {
            "romaji": [],
            "hiragana": [],
            "katakana": []
        }
    },
    {
        "kanji": "回",
        "meanings": [ "turn", "times", "time", "round", "occasion" ],
        "pronunciations": {
            "romaji": [],
            "hiragana": [],
            "katakana": []
        }
    },
    {
        "kanji": "寺",
        "meanings": [ "temple" ],
        "pronunciations": {
            "romaji": [],
            "hiragana": [],
            "katakana": []
        }
    },
    {
        "kanji": "地",
        "meanings": [ "earth", "ground" ],
        "pronunciations": {
            "romaji": [],
            "hiragana": [],
            "katakana": []
        }
    },
    {
        "kanji": "多",
        "meanings": [ "many", "much" ],
        "pronunciations": {
            "romaji": [],
            "hiragana": [],
            "katakana": []
        }
    },
    {
        "kanji": "光",
        "meanings": [ "light", "glittering", "shine", "shining", "optics" ],
        "pronunciations": {
            "romaji": [],
            "hiragana": [],
            "katakana": []
        }
    },
    {
        "kanji": "当",
        "meanings": [ "hit", "right", "appropriate" ],
        "pronunciations": {
            "romaji": [],
            "hiragana": [],
            "katakana": []
        }
    },
    {
        "kanji": "毎",
        "meanings": [ "every" ],
        "pronunciations": {
            "romaji": [],
            "hiragana": [],
            "katakana": []
        }
    },
    {
        "kanji": "池",
        "meanings": [ "lake", "moat", "pond" ],
        "pronunciations": {
            "romaji": [],
            "hiragana": [],
            "katakana": []
        }
    },
    {
        "kanji": "米",
        "meanings": [ "rice" ],
        "pronunciations": {
            "romaji": [],
            "hiragana": [],
            "katakana": []
        }
    },
    {
        "kanji": "羽",
        "meanings": [ "wing", "feather", "down", "plume", "fletching" ],
        "pronunciations": {
            "romaji": [],
            "hiragana": [],
            "katakana": []
        }
    },
    {
        "kanji": "考",
        "meanings": [ "thought", "consideration" ],
        "pronunciations": {
            "romaji": [],
            "hiragana": [],
            "katakana": []
        }
    },
    {
        "kanji": "肉",
        "meanings": [ "meat", "flesh" ],
        "pronunciations": {
            "romaji": [],
            "hiragana": [],
            "katakana": []
        }
    },
    {
        "kanji": "自",
        "meanings": [ "self", "oneself" ],
        "pronunciations": {
            "romaji": [],
            "hiragana": [],
            "katakana": []
        }
    },
    {
        "kanji": "色",
        "meanings": [ "color" ],
        "pronunciations": {
            "romaji": [],
            "hiragana": [],
            "katakana": []
        }
    },
    {
        "kanji": "行",
        "meanings": [ "line", "row" ],
        "pronunciations": {
            "romaji": [],
            "hiragana": [],
            "katakana": []
        }
    },
    {
        "kanji": "西",
        "meanings": [ "west" ],
        "pronunciations": {
            "romaji": [],
            "hiragana": [],
            "katakana": []
        }
    },
    {
        "kanji": "来",
        "meanings": [ "come", "to come" ],
        "pronunciations": {
            "romaji": [],
            "hiragana": [],
            "katakana": []
        }
    },
    {
        "kanji": "何",
        "meanings": [ "what" ],
        "pronunciations": {
            "romaji": [],
            "hiragana": [],
            "katakana": []
        }
    },
    {
        "kanji": "作",
        "meanings": [ "work", "production", "product" ],
        "pronunciations": {
            "romaji": [],
            "hiragana": [],
            "katakana": []
        }
    },
    {
        "kanji": "体",
        "meanings": [ "body" ],
        "pronunciations": {
            "romaji": [],
            "hiragana": [],
            "katakana": []
        }
    },
    {
        "kanji": "弟",
        "meanings": [ "younger sibling" ],
        "pronunciations": {
            "romaji": [],
            "hiragana": [],
            "katakana": []
        }
    },
    {
        "kanji": "図",
        "meanings": [ "diagram", "figure", "illustration" ],
        "pronunciations": {
            "romaji": [],
            "hiragana": [],
            "katakana": []
        }
    },
    {
        "kanji": "声",
        "meanings": [ "voice" ],
        "pronunciations": {
            "romaji": [],
            "hiragana": [],
            "katakana": []
        }
    },
    {
        "kanji": "売",
        "meanings": [ "sell", "to sell" ],
        "pronunciations": {
            "romaji": [],
            "hiragana": [],
            "katakana": []
        }
    },
    {
        "kanji": "形",
        "meanings": [ "shape", "form", "style" ],
        "pronunciations": {
            "romaji": [],
            "hiragana": [],
            "katakana": []
        }
    },
    {
        "kanji": "汽",
        "meanings": [ "steam", "vapor", "nearly" ],
        "pronunciations": {
            "romaji": [],
            "hiragana": [],
            "katakana": []
        }
    },
    {
        "kanji": "社",
        "meanings": [ "shrine" ],
        "pronunciations": {
            "romaji": [],
            "hiragana": [],
            "katakana": []
        }
    },
    {
        "kanji": "角",
        "meanings": [ "corner", "edge" ],
        "pronunciations": {
            "romaji": [],
            "hiragana": [],
            "katakana": []
        }
    },
    {
        "kanji": "言",
        "meanings": [ "word", "to say", "speech", "say" ],
        "pronunciations": {
            "romaji": [],
            "hiragana": [],
            "katakana": []
        }
    },
    {
        "kanji": "谷",
        "meanings": [ "valley", "lowland", "plain" ],
        "pronunciations": {
            "romaji": [],
            "hiragana": [],
            "katakana": []
        }
    },
    {
        "kanji": "走",
        "meanings": [ "run" ],
        "pronunciations": {
            "romaji": [],
            "hiragana": [],
            "katakana": []
        }
    },
    {
        "kanji": "近",
        "meanings": [ "near", "close" ],
        "pronunciations": {
            "romaji": [],
            "hiragana": [],
            "katakana": []
        }
    },
    {
        "kanji": "里",
        "meanings": [ "village", "hometuwn", "country", "countrysided" ],
        "pronunciations": {
            "romaji": [],
            "hiragana": [],
            "katakana": []
        }
    },
    {
        "kanji": "麦",
        "meanings": [ "wheat", "barley" ],
        "pronunciations": {
            "romaji": [],
            "hiragana": [],
            "katakana": []
        }
    },
    {
        "kanji": "画",
        "meanings": [ "picture", "drawing", "painting" ],
        "pronunciations": {
            "romaji": [],
            "hiragana": [],
            "katakana": []
        }
    },
    {
        "kanji": "東",
        "meanings": [ "east" ],
        "pronunciations": {
            "romaji": [],
            "hiragana": [],
            "katakana": []
        }
    },
    {
        "kanji": "京",
        "meanings": [ "capital city", "Tokyo", "Kyoto" ],
        "pronunciations": {
            "romaji": [],
            "hiragana": [],
            "katakana": []
        }
    },
    {
        "kanji": "夜",
        "meanings": [ "night" ],
        "pronunciations": {
            "romaji": [],
            "hiragana": [],
            "katakana": []
        }
    },
    {
        "kanji": "直",
        "meanings": [ "directly", "straight" ],
        "pronunciations": {
            "romaji": [],
            "hiragana": [],
            "katakana": []
        }
    },
    {
        "kanji": "国",
        "meanings": [ "country", "land", "large place", "nation", "domain", "state" ],
        "pronunciations": {
            "romaji": [],
            "hiragana": [],
            "katakana": []
        }
    },
    {
        "kanji": "姉",
        "meanings": [ "older sister", "sister" ],
        "pronunciations": {
            "romaji": [],
            "hiragana": [],
            "katakana": []
        }
    },
    {
        "kanji": "妹",
        "meanings": [ "younger sister", "sister" ],
        "pronunciations": {
            "romaji": [],
            "hiragana": [],
            "katakana": []
        }
    },
    {
        "kanji": "岩",
        "meanings": [ "rock" ],
        "pronunciations": {
            "romaji": [],
            "hiragana": [],
            "katakana": []
        }
    },
    {
        "kanji": "店",
        "meanings": [ "store", "shop" ],
        "pronunciations": {
            "romaji": [],
            "hiragana": [],
            "katakana": []
        }
    },
    {
        "kanji": "明",
        "meanings": [ "clear", "tomorrow", "bright" ],
        "pronunciations": {
            "romaji": [],
            "hiragana": [],
            "katakana": []
        }
    },
    {
        "kanji": "歩",
        "meanings": [ "walk", "step", "a step", "pawn" ],
        "pronunciations": {
            "romaji": [],
            "hiragana": [],
            "katakana": []
        }
    },
    {
        "kanji": "知",
        "meanings": [ "knowledge", "wisdom" ],
        "pronunciations": {
            "romaji": [],
            "hiragana": [],
            "katakana": []
        }
    },
    {
        "kanji": "長",
        "meanings": [ "long", "lenghty", "growing", "increasing", "excellent", "great", "elder" ],
        "pronunciations": {
            "romaji": [],
            "hiragana": [],
            "katakana": []
        }
    },
    {
        "kanji": "門",
        "meanings": [ "gate" ],
        "pronunciations": {
            "romaji": [],
            "hiragana": [],
            "katakana": []
        }
    },
    {
        "kanji": "昼",
        "meanings": [ "noon", "daytime" ],
        "pronunciations": {
            "romaji": [],
            "hiragana": [],
            "katakana": []
        }
    },
    {
        "kanji": "前",
        "meanings": [ "in front", "before", "previous" ],
        "pronunciations": {
            "romaji": [],
            "hiragana": [],
            "katakana": []
        }
    },
    {
        "kanji": "南",
        "meanings": [ "south" ],
        "pronunciations": {
            "romaji": [],
            "hiragana": [],
            "katakana": []
        }
    },
    {
        "kanji": "点",
        "meanings": [ "spot", "dot", "score", "grade", "mark", "point" ],
        "pronunciations": {
            "romaji": [],
            "hiragana": [],
            "katakana": []
        }
    },
    {
        "kanji": "室",
        "meanings": [ "room" ],
        "pronunciations": {
            "romaji": [],
            "hiragana": [],
            "katakana": []
        }
    },
    {
        "kanji": "後",
        "meanings": [],
        "pronunciations": {
            "romaji": [ "behind", "after", "rear" ],
            "hiragana": [],
            "katakana": []
        }
    },
    {
        "kanji": "春",
        "meanings": [ "spring" ],
        "pronunciations": {
            "romaji": [],
            "hiragana": [],
            "katakana": []
        }
    },
    {
        "kanji": "星",
        "meanings": [ "star" ],
        "pronunciations": {
            "romaji": [],
            "hiragana": [],
            "katakana": []
        }
    },
    {
        "kanji": "海",
        "meanings": [ "sea", "ocean", "large", "wide" ],
        "pronunciations": {
            "romaji": [],
            "hiragana": [],
            "katakana": []
        }
    },
    {
        "kanji": "活",
        "meanings": [ "life", "active" ],
        "pronunciations": {
            "romaji": [],
            "hiragana": [],
            "katakana": []
        }
    },
    {
        "kanji": "思",
        "meanings": [ "think", "thought" ],
        "pronunciations": {
            "romaji": [],
            "hiragana": [],
            "katakana": []
        }
    },
    {
        "kanji": "科",
        "meanings": [ "family", "grade", "department", "section" ],
        "pronunciations": {
            "romaji": [],
            "hiragana": [],
            "katakana": []
        }
    },
    {
        "kanji": "秋",
        "meanings": [ "autumn", "fall" ],
        "pronunciations": {
            "romaji": [],
            "hiragana": [],
            "katakana": []
        }
    },
    {
        "kanji": "茶",
        "meanings": [ "tea", "brown" ],
        "pronunciations": {
            "romaji": [],
            "hiragana": [],
            "katakana": []
        }
    },
    {
        "kanji": "計",
        "meanings": [ "plan", "total" ],
        "pronunciations": {
            "romaji": [],
            "hiragana": [],
            "katakana": []
        }
    },
    {
        "kanji": "風",
        "meanings": [ "wind" ],
        "pronunciations": {
            "romaji": [],
            "hiragana": [],
            "katakana": []
        }
    },
    {
        "kanji": "食",
        "meanings": [ "eat", "to eat", "meal" ],
        "pronunciations": {
            "romaji": [],
            "hiragana": [],
            "katakana": []
        }
    },
    {
        "kanji": "首",
        "meanings": [ "neck", "beginning", "first" ],
        "pronunciations": {
            "romaji": [],
            "hiragana": [],
            "katakana": []
        }
    },
    {
        "kanji": "夏",
        "meanings": [ "summer", "China" ],
        "pronunciations": {
            "romaji": [],
            "hiragana": [],
            "katakana": []
        }
    },
    {
        "kanji": "弱",
        "meanings": [ "weak", "weakness" ],
        "pronunciations": {
            "romaji": [],
            "hiragana": [],
            "katakana": []
        }
    },
    {
        "kanji": "原",
        "meanings": [ "plain", "field", "original" ],
        "pronunciations": {
            "romaji": [],
            "hiragana": [],
            "katakana": []
        }
    },
    {
        "kanji": "家",
        "meanings": [ "house", "home" ],
        "pronunciations": {
            "romaji": [],
            "hiragana": [],
            "katakana": []
        }
    },
    {
        "kanji": "帰",
        "meanings": [ "return", "to return", "come back" ],
        "pronunciations": {
            "romaji": [],
            "hiragana": [],
            "katakana": []
        }
    },
    {
        "kanji": "時",
        "meanings": [ "time" ],
        "pronunciations": {
            "romaji": [],
            "hiragana": [],
            "katakana": []
        }
    },
    {
        "kanji": "紙",
        "meanings": [ "paper" ],
        "pronunciations": {
            "romaji": [],
            "hiragana": [],
            "katakana": []
        }
    },
    {
        "kanji": "書",
        "meanings": [ "document", "book", "letter" ],
        "pronunciations": {
            "romaji": [],
            "hiragana": [],
            "katakana": []
        }
    },
    {
        "kanji": "記",
        "meanings": [ "statement", "incription", "mention", "describe" ],
        "pronunciations": {
            "romaji": [],
            "hiragana": [],
            "katakana": []
        }
    },
    {
        "kanji": "通",
        "meanings": [ "through", "pass through" ],
        "pronunciations": {
            "romaji": [],
            "hiragana": [],
            "katakana": []
        }
    },
    {
        "kanji": "馬",
        "meanings": [ "horse" ],
        "pronunciations": {
            "romaji": [],
            "hiragana": [],
            "katakana": []
        }
    },
    {
        "kanji": "高",
        "meanings": [ "high", "tall", "expensive", "maximum", "limit" ],
        "pronunciations": {
            "romaji": [],
            "hiragana": [],
            "katakana": []
        }
    },
    {
        "kanji": "強",
        "meanings": [ "strong", "powerful", "potent" ],
        "pronunciations": {
            "romaji": [],
            "hiragana": [],
            "katakana": []
        }
    },
    {
        "kanji": "教",
        "meanings": [ "to teach", "teachings" ],
        "pronunciations": {
            "romaji": [],
            "hiragana": [],
            "katakana": []
        }
    },
    {
        "kanji": "理",
        "meanings": [ "reason", "logic" ],
        "pronunciations": {
            "romaji": [],
            "hiragana": [],
            "katakana": []
        }
    },
    {
        "kanji": "細",
        "meanings": [ "thin", "fine", "slender" ],
        "pronunciations": {
            "romaji": [],
            "hiragana": [],
            "katakana": []
        }
    },
    {
        "kanji": "組",
        "meanings": [ "class", "group", "team", "set" ],
        "pronunciations": {
            "romaji": [],
            "hiragana": [],
            "katakana": []
        }
    },
    {
        "kanji": "船",
        "meanings": [ "ship", "vessel", "large ship" ],
        "pronunciations": {
            "romaji": [],
            "hiragana": [],
            "katakana": []
        }
    },
    {
        "kanji": "週",
        "meanings": [ "week" ],
        "pronunciations": {
            "romaji": [],
            "hiragana": [],
            "katakana": []
        }
    },
    {
        "kanji": "野",
        "meanings": [ "field", "plain", "natural", "prestine", "bare", "open" ],
        "pronunciations": {
            "romaji": [],
            "hiragana": [],
            "katakana": []
        }
    },
    {
        "kanji": "雪",
        "meanings": [ "snow", "white as snow", "cleanse" ],
        "pronunciations": {
            "romaji": [],
            "hiragana": [],
            "katakana": []
        }
    },
    {
        "kanji": "魚",
        "meanings": [ "fish" ],
        "pronunciations": {
            "romaji": [],
            "hiragana": [],
            "katakana": []
        }
    },
    {
        "kanji": "鳥",
        "meanings": [ "bird" ],
        "pronunciations": {
            "romaji": [],
            "hiragana": [],
            "katakana": []
        }
    },
    {
        "kanji": "黄",
        "meanings": [ "yellow" ],
        "pronunciations": {
            "romaji": [],
            "hiragana": [],
            "katakana": []
        }
    },
    {
        "kanji": "黒",
        "meanings": [ "black" ],
        "pronunciations": {
            "romaji": [],
            "hiragana": [],
            "katakana": []
        }
    },
    {
        "kanji": "場",
        "meanings": [ "place", "a place", "market", "a market" ],
        "pronunciations": {
            "romaji": [],
            "hiragana": [],
            "katakana": []
        }
    },
    {
        "kanji": "晴",
        "meanings": [ "clear", "to clear up" ],
        "pronunciations": {
            "romaji": [],
            "hiragana": [],
            "katakana": []
        }
    },
    {
        "kanji": "答",
        "meanings": [ "answer", "reply" ],
        "pronunciations": {
            "romaji": [],
            "hiragana": [],
            "katakana": []
        }
    },
    {
        "kanji": "絵",
        "meanings": [ "picture" ],
        "pronunciations": {
            "romaji": [],
            "hiragana": [],
            "katakana": []
        }
    },
    {
        "kanji": "買",
        "meanings": [ "buy", "to buy" ],
        "pronunciations": {
            "romaji": [],
            "hiragana": [],
            "katakana": []
        }
    },
    {
        "kanji": "朝",
        "meanings": [ "morning", "dynasty", "regime", "period" ],
        "pronunciations": {
            "romaji": [],
            "hiragana": [],
            "katakana": []
        }
    },
    {
        "kanji": "道",
        "meanings": [ "road", "way" ],
        "pronunciations": {
            "romaji": [],
            "hiragana": [],
            "katakana": []
        }
    },
    {
        "kanji": "番",
        "meanings": [ "number", "turn" ],
        "pronunciations": {
            "romaji": [],
            "hiragana": [],
            "katakana": []
        }
    },
    {
        "kanji": "間",
        "meanings": [ "space", "void", "between", "during" ],
        "pronunciations": {
            "romaji": [],
            "hiragana": [],
            "katakana": []
        }
    },
    {
        "kanji": "雲",
        "meanings": [ "cloud" ],
        "pronunciations": {
            "romaji": [],
            "hiragana": [],
            "katakana": []
        }
    },
    {
        "kanji": "園",
        "meanings": [ "field", "plantation", "garden", "park" ],
        "pronunciations": {
            "romaji": [],
            "hiragana": [],
            "katakana": []
        }
    },
    {
        "kanji": "数",
        "meanings": [ "number" ],
        "pronunciations": {
            "romaji": [],
            "hiragana": [],
            "katakana": []
        }
    },
    {
        "kanji": "新",
        "meanings": [ "new", "change", "reform" ],
        "pronunciations": {
            "romaji": [],
            "hiragana": [],
            "katakana": []
        }
    },
    {
        "kanji": "楽",
        "meanings": [ "music", "comfort", "enjoyment", "easy", "simplicity" ],
        "pronunciations": {
            "romaji": [],
            "hiragana": [],
            "katakana": []
        }
    },
    {
        "kanji": "話",
        "meanings": [ "talk" ],
        "pronunciations": {
            "romaji": [],
            "hiragana": [],
            "katakana": []
        }
    },
    {
        "kanji": "遠",
        "meanings": [ "distant", "far" ],
        "pronunciations": {
            "romaji": [],
            "hiragana": [],
            "katakana": []
        }
    },
    {
        "kanji": "電",
        "meanings": [ "lightning", "electricity" ],
        "pronunciations": {
            "romaji": [],
            "hiragana": [],
            "katakana": []
        }
    },
    {
        "kanji": "鳴",
        "meanings": [ "cry", "a cry", "crying" ],
        "pronunciations": {
            "romaji": [],
            "hiragana": [],
            "katakana": []
        }
    },
    {
        "kanji": "歌",
        "meanings": [ "song", "poetry" ],
        "pronunciations": {
            "romaji": [],
            "hiragana": [],
            "katakana": []
        }
    },
    {
        "kanji": "算",
        "meanings": [ "counting", "calculation" ],
        "pronunciations": {
            "romaji": [],
            "hiragana": [],
            "katakana": []
        }
    },
    {
        "kanji": "語",
        "meanings": [ "word", "term", "speech", "language" ],
        "pronunciations": {
            "romaji": [],
            "hiragana": [],
            "katakana": []
        }
    },
    {
        "kanji": "読",
        "meanings": [ "read", "to read" ],
        "pronunciations": {
            "romaji": [],
            "hiragana": [],
            "katakana": []
        }
    },
    {
        "kanji": "聞",
        "meanings": [ "hear" ],
        "pronunciations": {
            "romaji": [],
            "hiragana": [],
            "katakana": []
        }
    },
    {
        "kanji": "線",
        "meanings": [ "line", "level", "beam" ],
        "pronunciations": {
            "romaji": [],
            "hiragana": [],
            "katakana": []
        }
    },
    {
        "kanji": "親",
        "meanings": [ "parent", "elder" ],
        "pronunciations": {
            "romaji": [],
            "hiragana": [],
            "katakana": []
        }
    },
    {
        "kanji": "頭",
        "meanings": [ "head" ],
        "pronunciations": {
            "romaji": [],
            "hiragana": [],
            "katakana": []
        }
    },
    {
        "kanji": "曜",
        "meanings": [ "shine", "weekday", "day of the week" ],
        "pronunciations": {
            "romaji": [],
            "hiragana": [],
            "katakana": []
        }
    },
    {
        "kanji": "顔",
        "meanings": [ "face", "expression" ],
        "pronunciations": {
            "romaji": [],
            "hiragana": [],
            "katakana": []
        }
    }
]
